{
  "record_id": "7a454645485d33d4",
  "source_slug": "techinsights",
  "source_name": "TechInsights",
  "source_url": "https://www.techinsights.com/sales-and-marketing-professionals",
  "category": "Chip teardowns, die shots",
  "type": "Deep",
  "paywalled": false,
  "title": "Sales and Marketing Professionals",
  "published_date": "2026-06-19",
  "language": "en",
  "author": "",
  "word_count": 1140,
  "text": "Sales and Marketing Professionals\n\nTurn Complexity into Competitive Advantage. Align Campaigns with Market Reality.\n\nSales and marketing teams in the semiconductor industry are constantly navigating a maze of shifting customer needs, emerging technologies, and aggressive growth targets—all while managing internal misalignment and external market pressures. TechInsights gives you the data-backed clarity and confidence you need to reach the right audience, craft relevant messaging, and prove impact.\n\nGet Started\n\nHow TechInsights Helps You Win\n\nEmpower your decisions with actionable market intelligence, demand models, and competitive insights.\n\nIdentify the Right Markets and Opportunities\nTechInsights enables you to uncover and prioritize the highest-growth opportunities across key sectors like automotive, compute, smart home, power, and industrial. Our demand forecasts are segmented by end markets, technologies, and device features—giving you visibility into where the market is headed and how your solutions align. Whether you’re targeting AI-driven datacenters, EV platforms, or emerging wireless chipsets, we provide the clarity you need to focus your efforts where they’ll drive the most impact.\n\nCraft Messaging That Resonates\nWith TechInsights, your messaging isn’t guesswork—it’s grounded in real-world data and customer behavior. Our insights into benchmark product designs, teardowns, and design win data help you speak directly to evolving customer pain points. You’ll be able to validate product claims, tailor your value proposition by industry or region, and confidently build narratives that differentiate your offering in a crowded, technical market.\n\nEnable High-Impact Campaigns and Sales Plays\nWe equip you with the intelligence to develop sales plays and campaigns that hit the mark. Our data shows where customers are spending, what technologies they’re adopting, and what they’ll need next. With this information, you can build field marketing programs, outbound content, and account-based campaigns that align with actual purchase drivers. You'll also gain the tools to arm your sales teams with compelling, data-backed insights that shorten the sales cycle and improve win rates.\n\nDrive Alignment and Strategy Internally\nBy serving as a single source of truth, TechInsights helps unify your sales, marketing, product, and engineering teams. Our detailed market data supports strategic decisions around roadmap planning, channel strategies, pricing, and GTM alignment. You’ll spend less time debating assumptions and more time executing strategies informed by accurate, forecast-backed intelligence—all while fostering better collaboration across teams.\n\nLeveraging TechInsights Manufacturing Equipment Market Analysis to Bolster its Market Position\n\nA leading Capital Equipment company that develops, manufactures, markets, sells and services semiconductor assembly equipment for the global semiconductor and electronics industries needed to assure investors that its market position remains stable, and its growth projects are attainable.\n\nLearn More\n\nHow TechInsights’ Compute and Advanced Packaging Drove First-Mover Advantage in the Data Center Market\n\nA leading manufacturer of electronic components and solutions, integral to devices like smartphones, PCs, televisions, servers and cars sought TechInsights’ expertise to gain a comprehensive understanding of the data center ecosystem.\n\nLearn More\n\nMake an Impact That’s Measurable\n\nWith TechInsights, you can:\n\nShorten campaign planning cycles with validated market data\nImprove sales conversions through precise segmentation\nAlign resources to the most profitable opportunities\nProve marketing’s influence on revenue with greater clarity\nStay ahead of your competitors with continuous competitive tracking\n\nProducts Offered\n\nAdvanced Packaging: Assess the business impact of advanced packaging trends.\nAutomotive: Competitively design and plan for success.\nCompute: Gain a full understanding of semiconductor structures and process flows to drive your next-generation equipment.\nConnected Computing: Pinpoint competitive dynamics and anticipate trends in the market.\nConnected/Smart Home: Unlock opportunities to capture market share by developing product plans that meet future needs.\nConsumer Electronics: Enhance design and production planning processes.\nExecutive Insights: Timely, rapid insights on the megatrends shaping the semiconductor value chain.\nIoT Connectivity SoC: Unparalleled technical and cost analysis for essential IoT SoCs.\n\nManufacturing Analysis: Leverage insights about Fab capacity.\nMemory (Storage): Make data-driven design choices, know the competitive landscape, and understand the memory market dynamics.\nMobile RF: Refine your product roadmap, align with industry trends, and outpace competitors, ensuring your success in the challenging 5G Mobile RF landscape.\nPower Semiconductors: Deep technical analysis on the latest innovations in energy efficiency, power management, and low-power solutions to help you stay competitive and align your strategy.\nSensors: Deep technical analysis to better understand image sensors and image processing as key points of differentiation in the market.\nSmartphones, Tablets, Wearables: Insights into emerging trends and enabling technologies critical to the future.\n\nReady to Transform Your Go-to-Market Strategy?\n\n \n\nLet’s talk about how TechInsights can empower your sales and marketing team with the insights needed to hit your growth goals.\n\n \n\nCreate Account\n\nRequest a Demo\n\nFrequently Asked Questions\n\nHow does TechInsights help sales and marketing teams identify the right markets?\n\nTechInsights provides demand forecasts segmented by region, application, and technology—giving you clarity on where the semiconductor market is growing and how your products align. Whether you're targeting AI, automotive, IoT, or industrial applications, you’ll have data to prioritize high-impact sectors.\n\nCan TechInsights improve our messaging and positioning?\n\nYes. Our insights are grounded in real product teardowns, competitive benchmarking, and design win analysis. This allows you to craft messaging based on real customer pain points, validate product claims, and tailor communications to resonate by industry, region, or buyer role.\n\nWhat types of data and reports are available?\n\nOur offerings include demand forecasts, design win analysis, product teardowns, market share data, competitor tracking, and vertical-specific insights across sectors like automotive, compute, power, smart home, and more.\n\nJune 19, 2026\n\nGoogle I/O 2026: Gemini for Home Takes Center Stage\nGoogle I/O 2026 focused on Gemini for Home, AI-powered smart devices, and agentic AI, signaling a software-first future for the smart home market.\n\nLearn More\n\nJune 18, 2026\n\nPC and Tablet Market Trends | AI PCs, Apple M5 & Memory Costs\nDiscover the latest PC and tablet market trends, including AI PCs, Apple M5 devices, Intel Panther Lake, processor forecasts, tablet market share, and the impact of rising memory costs.\n\nLearn More\n\nJune 17, 2026\n\nGame Console Forecast 2030: Rising Prices, Declining Shipments, and the Future of Gaming\nDiscover why rising memory costs, higher console prices, and longer upgrade cycles are expected to slow game console shipments through 2030. Explore the outlook for Nintendo Switch 2, PlayStation, and Xbox in the latest TechInsights forecast.\n\nLearn More\n\nThe Authoritative Information Platform to the Semiconductor Industry.\n\nDiscover why TechInsights stands as the semiconductor industry's most trusted source for actionable, in-depth intelligence.\n\n \n\nAbout TechInsights\n\nWho We Are\n\nAbout Us\n\nInvestments\n\nCareers\n\nCommunity Involvement\n\nOur Experts\n\nTrust Center\n\nKey Topics\n\nSustainability\n\nArtificial Intelligence\n\nChinese Developments\n\nChiplets\n\nCapabilities\n\nReverse Engineering\n\nMarket Intelligence\n\nCost Analysis\n\nIntellectual Property Services\n\nGet in Touch\n\nContact\n\nContact Us\n\nOffice Locations\n\nSales Inquiry\n\nMedia Relations\n\nLatest Insights\n\nResources\n\nBlogs\n\nWebinars\n\nFeatured Reports\n\nPodcasts\n\nCase Studies\n\n1-877-826-4447\n\n1891 Robertson Rd #500, Nepean, ON K2H 5B7\n\nCopyright © 2026 TechInsights Inc. All rights reserved.\n\nAccessibility | Privacy Policy | Terms & Conditions | Conflict of Interest & Confidential Information | Ethics & Compliance",
  "image_urls": [
    "https://www.techinsights.com/sites/default/files/2025-05/sales-marketing-professionals.jpg",
    "https://www.techinsights.com/sites/default/files/2025-04/capital-equipment-techinsights.jpg",
    "https://www.techinsights.com/sites/default/files/styles/teaser/public/2026-06/google-io-2026-preview.jpg?h=9ea59734&itok=mclT1MLs",
    "https://www.techinsights.com/sites/default/files/styles/teaser/public/2026-06/pc-tablet-market-trends-preview.jpg?h=9ea59734&itok=isO-wYRg",
    "https://www.techinsights.com/sites/default/files/styles/teaser/public/2026-06/cigame-console-forecast-2030-preview.jpg?h=9ea59734&itok=wTaDn__3",
    "https://www.techinsights.com/sites/default/files/2024-08/yt.png",
    "https://www.techinsights.com/sites/default/files/2023-09/store-apple.png",
    "https://www.techinsights.com/sites/default/files/2023-09/store-google-play.png",
    "https://www.techinsights.com/sites/default/files/2026-02/Ecovadis%20Badge%202026%20%282%29_0.png",
    "https://www.techinsights.com/sites/default/files/2025-03/iso-27001.png"
  ],
  "collected_at": "2026-06-22T19:25:19.000Z"
}