{
  "record_id": "d7833c2666d0a52c",
  "source_slug": "semiconductor_engineering",
  "source_name": "Semiconductor Engineering",
  "source_url": "https://semiengineering.com/research-bits-july-21/",
  "category": "Chip design, packaging, EDA",
  "type": "Deep",
  "paywalled": false,
  "title": "Research Bits: July 21",
  "published_date": "2026-07-21",
  "language": "en",
  "author": "Jesse Allen",
  "word_count": 1451,
  "text": "Home\n\nSystems & Design\n\nLow Power - High Performance\n\nManufacturing, Packaging & Materials\n\nTest, Measurement & Analytics\n\nAuto, Security & Edge AI\n\nSpecial Reports\n\nBusiness & Startups\n\nJobs\n\nKnowledge Center\n\nTechnical Papers\n\nHome';\nAI/ML/DLArchitecturesAutomotive/ AerospaceCommunication/Data MovementDesign & VerificationLithographyManufacturingMaterialsMemoryOptoelectronics / PhotonicsPackagingPower & PerformanceQuantumSecurityTest, Measurement, Analytics tech papersTransistorsZ-End Applications\n\nEvents & Webinars\n\nEvents\nWebinars\n\nVideos & Research\n\nVideos\nIndustry Research\n\nNewsletters & Store\n\nNewsletters\nStore\n\nMENU\n\nHome\n\nSpecial Reports\n\nSystems & Design\n\nLow Power-High Performance\n\nManufacturing, Packaging & Materials\n\nTest, Measurement & Analytics\n\nAuto, Security & Edge AI\n\nKnowledge Center\n\nVideos\n\nStartup Corner\n\nBusiness & Startups\n\nJobs\n\nTechnical Papers\n\nEvents\n\nWebinars\n\nIndustry Research\n\nNewsletters\nStore\n\nSpecial Reports\n\nHome >\nLow Power-High Performance >\nResearch Bits: July 21\n\nShares\n\nLow Power-High Performance\n\nResearch Bits: July 21\n\nShares\n\nThin TMD transistors; diamond defect detection; roll-to-roll litho.\n\nJuly 21st, 2026 -\n\nBy: Jesse Allen\n\nThin TMD transistors\nResearchers from Chalmers University of Technology and Stanford University fabricated transistors from three different atomically thin 2D semiconductors with channel widths as small as 25nm.\n“These are some of the slimmest high-performance transistors demonstrated in two-dimensional semiconductors,” said Anton Persson, assistant professor at Chalmers University of Technology, in a press release. “What is particularly encouraging, and actually surprised us, is that the transistors remained well-behaved even when shrunk to dimensions relevant for future industrial technologies. That has been a major uncertainty in the field.”\nThe nanoribbon transistors were fabricated from three different monolayer transition metal dichalcogenides: molybdenum disulfide, tungsten disulfide, and tungsten diselenide. To prevent tears or peeling during fabrication, the team developed a “dog-bone” structure with an extremely narrow transistor channel and wider regions under the electrical contacts to help anchor the material in place. An advanced multi-patterning technique that etched the material in two steps from different directions was also used.\n“The 2D transistors made of tungsten disulfide were especially notable, as their current density improved by more than a hundred times compared to previous demonstrations, thanks to better material quality and improved metal contacts,” said Persson.\n“Our findings don’t mean that atomically thin 2D semiconductors are ready to replace silicon tomorrow,” added Eric Pop, professor at Stanford University, in a press release. “But it shows that one of the key scaling concerns may be far less limiting than previously thought.” [1]\nDiamond defect detection\nResearchers from Rice University and DEVCOM Army Research Laboratory developed a custom Python-based software tool to rapidly analyze data from high-resolution X-ray diffraction and detect dislocation density defects in diamond and other wide-bandgap semiconductor materials. The software analyzes diffraction patterns, picks up on dislocations and irregularities in the atomic lattice, and calculates their density in a given material.\n“Dislocations can disrupt how charge and heat move through the material, which impacts how efficient and reliable a device is, and how easy it is to manufacture at scale,” said Xiang Zhang, assistant research professor of materials science and nanoengineering at Rice, in a statement.\nThe framework was tested by analyzing four commercially available grades of single-crystal diamond with different expected levels of crystal quality. The automated workflow was able to distinguish among the materials, identifying electronic-grade diamond as having the lowest defect density and most uniform crystal quality. Heteroepitaxial diamond grown on a non-diamond substrate exhibited the highest defect density and greatest structural disorder.\nThe team also successfully applied the workflow to gallium nitride. Next, they plan to expand the range of materials and defect types it can analyze. [2]\nRoll-to-roll litho\nResearchers from the Korea Institute of Machinery and Materials (KIMM) developed a roll-to-roll maskless digital lithography system for continuous patterning of flexible substrates with line widths below 10μm.\nThe system combines Digital Micromirror Device (DMD)-based exposure technology to selectively project UV light onto designated areas of a substrate. A dedicated exposure module and a high-precision web-transport control system enables continuous roll-to-roll operation, while vision-based measurements adjust the projected pattern in real time, compensating for positional errors and substrate deformation.\nBecause the patterns can be generated and modified through software control, the approach doesn’t need conventional photomasks and can support continuous, large-area manufacturing over long substrate lengths.\n“The R2R digital lithography system is a key platform technology for the mass production of flexible electronic devices. We expect it to be used in a wide range of applications, including flexible printed circuit boards, high-resolution flexible electronics, and semiconductor packaging,” said Won Seok Chang, director of the Nano-convergence Manufacturing Research Division at KIMM, in a statement. “The technology can also be applied to digital exposure processes for patterning roll surfaces, further broadening its industrial applications.” [3]\nReferences\n[1] T. Peña, A.E.O. Persson, A. Krayev, et al. Scaling nanoribbon transistors with monolayer transition metal dichalcogenides. Nat. Nanotechnol. 21, 803–809 (2026). https://doi.org/10.1038/s41565-026-02161-w\n[2] T. Gray, E. J. Garratt, X. Zhang, et al. “High Throughput X-Ray Characterization of Defects in Wide-Bandgap Semiconductors.” Advanced Materials 38, no. 39 (2026): e73678. https://doi.org/10.1002/adma.73678\n[3] J. Choi, W. S. Lee, G. Kim, et al. DMD-based adaptive lithography system for real-time substrate deformation compensation. International Journal of Optomechatronics, 20(1). (2026). https://doi.org/10.1080/15599612.2026.2635849\n\nShares\n\nTags: 2D semiconductors Chalmers University of Technology defect detection defects DEVCOM Army Research Laboratory diamond flexible electronics inspection KIMM Korea Institute of Machinery and Materials lithography Rice University roll-to-roll processing Stanford University TMDs transition-metal dichalcogenides wide bandgap semiconductors X-ray diffraction\n\nJesse Allen   (all posts)\n\nJesse Allen is the Knowledge Center administrator and a senior editor at Semiconductor Engineering.\n\nLeave a Reply Cancel reply\n\nTechnical Papers\nHW-based Methods to Dynamically Throttle AI Performance (Princeton University) July 21, 2026 by Technical Paper LinkMonolithic 3D-DRAM with Oxide-Semiconductor Architecture (imec, KU Leuven, Samsung, Lam) July 21, 2026 by Technical Paper LinkGraph Transformer Speeds IC Interconnect Signal Integrity Analysis (Buffalo, Stuttgart, IBM) July 20, 2026 by Technical Paper Link3D Mask Effects Enhance Imaging in High-NA EUV and Hyper-NA EUV Litho (Fraunhofer, ASML) July 20, 2026 by Technical Paper LinkInference Accelerator that Integrates Compute-in-Interconnect and Memory to Mitigate the Memory Wall (NUS) July 20, 2026 by Technical Paper Link\n\nKnowledge Centers Entities, people and technologies explored\n\nRelated Articles\n\nFlash Getting Stacked High-Bandwidth Version\n\nInspired by HBM, HBF could improve AI efficiency in 3D flash memory.\n\nby Bryon Moyer\n\nCan Edge AI Keep Up?\n\nAs models evolve faster than silicon cycles, experts weigh how much adaptability architects can afford without sacrificing power, area, or efficiency.\n\nby Ann Mutschler\n\nChiplets Need A New Workflow\n\nMulti-die assemblies are facing full system-level challenges, but engineering teams need coordinated and repeatable ways to identify risks early and scale reliably.\n\nby Ann Mutschler\n\nAgentic AI Is Changing Data Center Architectures\n\nStandalone GPUs are being replaced by heterogeneous SoCs and chiplets that combine CPUs, GPUs, and NPUs to eliminate memory bottlenecks, reduce latency, and boost efficiency.\n\nby Ann Mutschler\n\nGates Add Functionality, But Wires Create Problems\n\nWires are treated as a lesser concern, but their neglect is becoming critical at advanced nodes.\n\nby Brian Bailey\n\nWhere Does Quantum Computing Stand?\n\nIt's slowly emerging from research and heading toward high-volume production.\n\nby Bryon Moyer\n\nAI Is Rewriting The IP Playbook\n\nAs the semiconductor ecosystem pivots to AI, it is transforming how IP is created, verified, managed, and sold.\n\nby Ann Mutschler\n\nA New Era For Co-Processing\n\nProcessor architectures are evolving faster than ever, but they still lag the pace of AI development. Chip architects must predict what will be required tomorrow in designs today.\n\nby Brian Bailey\n\nBringing Design Data Management ... KeysightBlog Review: July 22 Jesse Allen\n\nAbout\n\nAbout us\nContact us\nAdvertising on SemiEng\nNewsletter SignUp\n\nNavigation\n\nHomepage\nSpecial Reports\nSystems & Design\nLow Power-High Perf\nManufacturing, Packaging & Materials\nTest, Measurement & Analytics\nAuto, Security & Edge AI\n\nVideos\nJobs\nTechnical Papers\nEvents\nWebinars\nKnowledge Centers\n\nIndustry Research\nBusiness & Startups\nNewsletters\nStore\n\nConnect With Us\n\nFacebook\nTwitter @semiEngineering\nLinkedIn\nYouTube\n\nCopyright ©2013-2026 SMG   |  Terms of Service  |  Privacy Policy\n\nThis site uses cookies. By continuing to use our website, you consent to our Cookies PolicyACCEPT Manage consent\n\nPrivacy Overview\nThis website uses cookies to improve your experience while you navigate through the website. The cookies that are categorized as necessary are stored on your browser as they are essential for the working of basic functionalities of the website. We al...\n\nNecessary\n\nNecessary\n\nAlways Enabled\n\nNecessary cookies are absolutely essential for the website to function properly. This category only includes cookies that ensures basic functionalities and security features of the website. These cookies do not store any personal information.\n\nNon-necessary\n\nNon-necessary\n\nAny cookies that may not be particularly necessary for the website to function and is used specifically to collect user personal data via analytics, ads, other embedded contents are termed as non-necessary cookies. It is mandatory to procure user consent prior to running these cookies on your website.\n\nSAVE & ACCEPT\n\nSearch resultsNo results foundFiltersShow filtersSort by: ••Filter options",
  "teaser": false,
  "image_urls": [],
  "collected_at": "2026-07-22T11:49:44.000Z"
}