{
  "record_id": "ce8efa8921905125",
  "source_slug": "war_on_the_rocks",
  "source_name": "War on the Rocks",
  "source_url": "https://warontherocks.com/episode/thinkingtheunthinkable/45523/revisiting-irans-nuclear-threshold/",
  "category": "Defense, national security",
  "type": "Flow",
  "paywalled": false,
  "title": "Revisiting Iran's Nuclear Threshold",
  "published_date": "2026-07-03",
  "language": "en",
  "author": "",
  "word_count": 138,
  "text": "Thinking the Unthinkable with Ankit Panda\nA bi-weekly podcast featuring in-depth analysis and insight on the perils of a new nuclear age, with Ankit Panda.\n\nBecome a member\n\nRevisiting Iran’s Nuclear Threshold\nThinking the Unthinkable with Ankit Panda\nEric Brewer and Ankit Panda\nJuly 3, 2026\n\nSign up now and start listening to \"Thinking the Unthinkable with Ankit Panda!\"Already a member? Sign In to have access to our podcasts\n\nEpisode Notes:\nAnkit Panda speaks with Eric Brewer about his Texas National Security Review article on how Iran managed — and ultimately mismanaged — its nuclear threshold status. Setting aside the 2026 war itself, Brewer examines the timeline from the Oct. 7, 2023 Hamas-led attacks on Israel to the 2025 \"Midnight Hammer\" strikes, asking why Iran's nuclear latency failed to deter Israel.\nImage: Dean Calma / IAEA via Flickr",
  "image_urls": [],
  "collected_at": "2026-07-05T11:22:50.000Z"
}