{
  "record_id": "483862d1041b1600",
  "source_slug": "ars_technica",
  "source_name": "Ars Technica",
  "source_url": "https://arstechnica.com/gadgets/2026/06/sony-erases-digital-content-from-libraries-were-reminded-we-dont-own-what-we-buy/",
  "category": "Tech, science, policy",
  "type": "Flow",
  "paywalled": false,
  "title": "Sony erases digital content from libraries; we're reminded we don’t own what we buy",
  "published_date": "2026-06-29",
  "language": "en",
  "author": "Scharon Harding",
  "word_count": 439,
  "text": "Story text\n\nSize\n\nSmall\nStandard\nLarge\n\nWidth\n*\n\nStandard\nWide\n\nLinks\n\nStandard\nOrange\n\n* Subscribers only\n  Learn more\n\nSony recently informed its PlayStation customers in the United Kingdom that they will no longer be able to watch previously purchased movies and shows from production and distribution company StudioCanal. As of September 1, affected customers will no longer be able to stream 551 titles from the PlayStation Store.\nIn a legal notice first spotted by gaming news outlet PlayStation LifeStyle, Sony said that affected customers will lose the ability to stream titles including Outrage: Way of the Yakuza, Paddington, Paddington 2, Pan’s Labyrinth, Rambo 3, Terminator 2: Judgment Day, and The Boy in the Striped Pajamas “due to our content licensing agreements.” As of September, Sony will remove any affected titles that UK users bought from their PlayStation library, per the notice.\n\nArs VideoWhat Happens to the Developers When AI Can Code? | Ars FrontiersIt’s possible that Sony may still make a deal with StudioCanal by September 1, or even after, that would allow users to keep watching the content they bought. This happened in 2023, when Sony said it would have to pull 1,318 seasons of Discovery shows from customers’ libraries. A few weeks after its announcement, Sony said that it would not pull the content because it had updated its licensing arrangements with Discovery.\n\nStill, affected customers shouldn’t keep their hopes too high. Sony already pulled 314 StudioCanal titles from libraries in Germany and Austria in 2022. More recently, Sony deleted people’s Funimation digital libraries after it decided to merge the anime streaming service with Crunchyroll. Sony has also been scaling down its digital store and stopped selling movie and show rentals and purchases in August 2021. Even if StudioCanal were willing to make a deal with Sony, it’s feasible that Sony has less interest in retaining digital titles than before.\nRegardless, the incident is a reminder that we don’t own the stuff we purchase digitally . Instead, digital rentals and purchases are merely long-term licenses that are only valid for as long as the streaming service has the right to distribute said content. Often, that’s a finite amount of time.\nStill, Sony’s announcement has frustrated some, including those who believe Sony should offer refunds or who think digital stores should stop using terms like “purchase” for long-term rentals. \n\nScharon Harding\n\nSenior Technology Reporter\n\nScharon Harding\n\nSenior Technology Reporter\n\nScharon is a Senior Technology Reporter at Ars Technica writing news, reviews, and analysis on consumer gadgets and services. She's been reporting on technology for over 10 years, with bylines at Tom’s Hardware, Channelnomics, and CRN UK.\n\n269 Comments",
  "image_urls": [
    "https://cdn.arstechnica.net/wp-content/uploads/2020/06/abomb8-300x200.jpg",
    "https://cdn.arstechnica.net/wp-content/uploads/2020/06/abomb8-1152x648.jpg",
    "https://cdn.arstechnica.net/wp-content/uploads/2021/09/scharon-harding-headshot.jpg"
  ],
  "collected_at": "2026-07-01T12:36:36.000Z"
}