{
  "record_id": "93d430ce90c02a12",
  "source_slug": "ars_technica",
  "source_name": "Ars Technica",
  "source_url": "https://arstechnica.com/ai/2026/07/googles-ai-buildout-drove-37-increase-in-electricity-use-in-2025/",
  "category": "Tech, science, policy",
  "type": "Flow",
  "paywalled": false,
  "title": "Google’s AI buildout drove 37% increase in electricity use in 2025",
  "published_date": "2026-07-02",
  "language": "en",
  "author": "Jeremy Hsu",
  "word_count": 757,
  "text": "Story text\n\nSize\n\nSmall\nStandard\nLarge\n\nWidth\n*\n\nStandard\nWide\n\nLinks\n\nStandard\nOrange\n\n* Subscribers only\n  Learn more\n\nGoogle reported that its annual electricity consumption rose by 37 percent in 2025—the largest increase in the company’s history as Silicon Valley’s AI data center buildout continues. But the tech giant says it kept operational carbon emissions down by continuing to purchase massive amounts of clean energy.\nThe company’s latest sustainability report acknowledges that Google’s total electricity usage has increased by more than 250 percent since 2019, which the company attributed to ongoing growth in Google Cloud, YouTube video streaming, and data center construction and operations supporting various AI products and services. The unprecedented 37 percent annual increase is part of an ongoing trend, given how Google’s total electricity consumption also grew by 27 percent in 2024.\n“While the path to achieving our climate ambitions will not be linear—given our AI infrastructure buildout is currently accelerating faster than the grid is decarbonizing—we remain focused on scaling abundant and affordable clean power globally and progressing technological innovations that drive down emissions across our operations and the broader industry,” according to the Google sustainability report.\nAs the bulk of electricity usage, Google’s data centers consumed more than 42 million megawatt-hours of electricity in 2025 compared to 30.6 million megawatt-hours of electricity in 2024. That means Google’s data center energy usage rivals the electricity consumption of entire countries such as New Zealand, Denmark, and Nigeria. More self-reported details from Google are available in the full sustainability report, including water consumption numbers for various data center campuses.\n\nArs VideoHow Scientists Respond to Science DeniersDespite the steep rise in electricity consumption, Google reported actually reducing operational emissions by 2 percent over the same year period. Such apparent “decoupling of electricity-related emissions” from growth in electricity usage is potentially promising, but Google said it would need to boost “clean energy investments and closer partnerships with local stakeholders in the years ahead.”\n\nThe company also noted that its supply chain emissions from its contracted manufacturers and suppliers actually grew by 25 percent because of “an Asia-Pacific supply chain operating on grids that remain undersupplied with carbon-free energy.”\nThe carbon-free energy goal\nGoogle has been matching 100 percent of its electricity consumption with renewable energy purchases every year across its global operations, a practice that it has adopted for nine years running. In 2025, the company’s purchase agreements encompassing 12 gigawatts of “net-new clean energy” represented the largest annual total in the company’s history.\nBut it also acknowledged that companies can merely claim to rely on 100 percent renewable power while still using power generated by fossil fuels in local power grids. Accordingly, Google says it has renewed its emphasis on a “24/7 carbon-free energy ambition” that gets into more granular accounting by focusing on certificates representing hourly and local matches for clean energy.\nTo its credit, Google has become one of the world’s largest investors in clean energy technology, according to Michael Thomas, CEO of the Cleanview data platform that tracks renewable energy and data center projects. But his analysis of Google’s data center power strategy suggests that Google has pivoted to an “Everything Everywhere All at Once” strategy that encompasses everything from renewables to natural gas generation.\nGoogle’s broader investments include efforts to commercialize “advanced nuclear, fusion energy, enhanced geothermal, long-duration energy storage, and natural gas with carbon capture and storage.” The company’s sustainability report highlighted investments of more than $3.8 billion between 2010 and 2025 that are expected to bring 7.5 gigawatts of clean energy online.\nHowever, in an April 2026 newsletter, Thomas pointed to Google’s $40 billion investment in Texas data centers as including a campus potentially powered by a 933-megawatt natural gas power plant without carbon capture technology. The natural gas plant’s turbines could produce 4.5 million tons of carbon dioxide annually.\nA Google spokesperson told Thomas that the company has not yet signed an agreement for how much power Google’s data center might draw from the natural gas plant.\n\nJeremy Hsu\n\nTech Reporter\n\nJeremy Hsu\n\nTech Reporter\n\nJeremy Hsu is a reporter exploring a wide range of topics across deep tech and AI. He has previously written for New Scientist, Scientific American, IEEE Spectrum, Wired, Undark Magazine and MIT Tech Review, among many other publications, about topics such as deepfakes, data centers, drones, battery tech, robotics, and GPS jamming. He also has a Master of Arts in Journalism from NYU, and a bachelor's degree from University of Pennsylvania in History and Sociology of Science, with a minor in English.\n\n11 Comments",
  "image_urls": [
    "https://cdn.arstechnica.net/wp-content/uploads/2026/07/GettyImages-2246163658-640x351.jpg",
    "https://cdn.arstechnica.net/wp-content/uploads/2026/07/GettyImages-2246163658-1152x648.jpg",
    "https://cdn.arstechnica.net/wp-content/uploads/2026/04/linkedin-profile-picture-headshot-JPG.jpg"
  ],
  "collected_at": "2026-07-02T12:10:50.000Z"
}